server.py
mseep_math_mcp-0.1.3.dist-info/METADATA
mseep_math_mcp-0.1.3.dist-info/WHEEL
mseep_math_mcp-0.1.3.dist-info/top_level.txt
mseep_math_mcp-0.1.3.dist-info/RECORD
