Metadata-Version: 2.4
Name: mseep-math-mcp
Version: 0.1.3
Summary: Add your description here
Author-email: mseep <support@skydeck.ai>
Requires-Python: >=3.13
Requires-Dist: mcp[cli]>=1.3.0
Requires-Dist: numpy>=2.2.3
